swaggerjmx_diff/__init__.py
swaggerjmx_diff/diff.py
swaggerjmx_diff/tools.py
swaggerjmx_diff/cli/__init__.py
swaggerjmx_diff/cli/cli.py
swaggerjmx_diff/cli/plugin.py
swaggerjmx_diff/cli/scaffold.py
swaggerjmx_diff-1.0.4.dist-info/LICENSE
swaggerjmx_diff-1.0.4.dist-info/METADATA
swaggerjmx_diff-1.0.4.dist-info/WHEEL
swaggerjmx_diff-1.0.4.dist-info/entry_points.txt
swaggerjmx_diff-1.0.4.dist-info/top_level.txt
swaggerjmx_diff-1.0.4.dist-info/RECORD
