Metadata-Version: 2.1
Name: swaggerjmx-diff
Version: 1.0.4
Summary: swaggerjmx-diff
Home-page: https://github.com/Pactortester
Author: lijiawei
Author-email: 1456470136@qq.com
License: MIT Licence
Keywords: pip,swaggerjmx-diff,swaggerjmx,diff
Platform: any
Classifier: License :: OSI Approved :: MIT License
Classifier: Development Status :: 5 - Production/Stable
Classifier: Environment :: Console :: Curses
Classifier: Operating System :: MacOS
Classifier: Operating System :: POSIX
Classifier: Operating System :: Microsoft :: Windows
Classifier: Programming Language :: Python :: 3 :: Only
Classifier: Programming Language :: Python :: 3.6
Classifier: Programming Language :: Python :: 3.7
Classifier: Programming Language :: Python :: 3.8
Classifier: Programming Language :: Python :: Implementation :: CPython
Classifier: Topic :: Security
Classifier: Topic :: Internet :: WWW/HTTP
Classifier: Topic :: Internet :: Proxy Servers
Classifier: Topic :: System :: Networking :: Monitoring
Classifier: Topic :: Software Development :: Testing
Classifier: Typing :: Typed
Requires-Dist: deepdiff (~=5.5.0)
Requires-Dist: loguru (~=0.5.3)
Requires-Dist: allure-pytest (~=2.9.43)
Requires-Dist: allure-python-commons (~=2.9.43)
Requires-Dist: requests (~=2.25.1)
